{
  "cat": "🐱",
  "dog": "🐶",
  "elephant": "🐘",
  "lion": "🦁",
  "tiger": "🐯",
  "bear": "🐻",
  "panda": "🐼",
  "koala": "🐨",
  "pig": "🐷",
  "cow": "🐮",
  "horse": "🐴",
  "unicorn": "🦄",
  "rabbit": "🐰",
  "mouse": "🐭",
  "hamster": "🐹",
  "fox": "🦊",
  "monkey": "🐵",
  "chicken": "🐔",
  "penguin": "🐧",
  "bird": "🐦",
  "duck": "🦆",
  "owl": "🦉",
  "frog": "🐸",
  "turtle": "🐢",
  "snake": "🐍",
  "dinosaur": "🦕",
  "trex": "🦖",
  "whale": "🐋",
  "dolphin": "🐬",
  "fish": "🐟",
  "octopus": "🐙",
  "butterfly": "🦋",
  "bee": "🐝",
  "ladybug": "🐞",
  "snail": "🐌",
  "crab": "🦀",
  "bug": "🐛",
  "zebra": "🦓",
  "giraffe": "🦒",
  "hippo": "🦛",
  "gorilla": "🦍",
  "wolf": "🐺",
  "deer": "🦌",
  "sheep": "🐑",
  "goat": "🐐",
  "camel": "🐪",
  "kangaroo": "🦘",
  "sloth": "🦥",
  "hedgehog": "🦔",
  "raccoon": "🦝",
  "squirrel": "🐿️",
  "bat": "🦇",
  "seal": "🦭",
  "shark": "🦈",
  "jellyfish": "🪼",
  "starfish": "⭐",
  "shrimp": "🦐",
  "lobster": "🦞",
  "squid": "🦑",
  "ant": "🐜",
  "spider": "🕷️",
  "scorpion": "🦂",
  "mosquito": "🦟",
  "cricket": "🦗",
  "worm": "🪱",
  "parrot": "🦜",
  "flamingo": "🦩",
  "peacock": "🦚",
  "swan": "🦢",
  "rooster": "🐓",
  "turkey": "🦃",
  "eagle": "🦅",
  "dove": "🕊️",
  "crocodile": "🐊",
  "lizard": "🦎",
  "dragon": "🐉",

  "fairy": "🧚",
  "mermaid": "🧜",
  "wizard": "🧙",
  "genie": "🧞",
  "ghost": "👻",
  "alien": "👽",
  "robot": "🤖",
  "monster": "👾",
  "vampire": "🧛",
  "zombie": "🧟",
  "ogre": "👹",
  "troll": "🧌",
  "princess": "👸",
  "prince": "🤴",
  "ninja": "🥷",
  "superhero": "🦸",
  "pirate": "🏴‍☠️",
  "baby": "👶",
  "angel": "👼",
  "clown": "🤡",

  "sun": "☀️",
  "moon": "🌙",
  "star": "⭐",
  "rainbow": "🌈",
  "cloud": "☁️",
  "rain": "🌧️",
  "snow": "❄️",
  "snowflake": "❄️",
  "flower": "🌸",
  "tree": "🌲",
  "plant": "🌱",
  "leaf": "🍃",
  "mushroom": "🍄",
  "rose": "🌹",
  "sunflower": "🌻",
  "tulip": "🌷",
  "blossom": "🌼",
  "mountain": "⛰️",
  "volcano": "🌋",
  "beach": "🏖️",
  "island": "🏝️",
  "ocean": "🌊",
  "desert": "🏜️",
  "forest": "🌳",
  "cactus": "🌵",
  "tornado": "🌪️",
  "wind": "🌬️",
  "ice": "🧊",
  "web": "🕸️",

  "planet": "🪐",
  "ufo": "🛸",
  "comet": "☄️",
  "earth": "🌍",
  "world": "🌍",

  "apple": "🍎",
  "banana": "🍌",
  "orange": "🍊",
  "grape": "🍇",
  "strawberry": "🍓",
  "watermelon": "🍉",
  "peach": "🍑",
  "cherry": "🍒",
  "lemon": "🍋",
  "pineapple": "🍍",
  "coconut": "🥥",
  "mango": "🥭",
  "kiwi": "🥝",
  "blueberry": "🫐",
  "pear": "🍐",

  "pizza": "🍕",
  "burger": "🍔",
  "hotdog": "🌭",
  "taco": "🌮",
  "fries": "🍟",
  "popcorn": "🍿",
  "pretzel": "🥨",
  "egg": "🥚",
  "bread": "🍞",
  "cheese": "🧀",
  "bacon": "🥓",
  "pancake": "🥞",
  "icecream": "🍦",
  "cake": "🎂",
  "cookie": "🍪",
  "candy": "🍬",
  "chocolate": "🍫",
  "donut": "🍩",
  "cupcake": "🧁",
  "pie": "🥧",
  "tomato": "🍅",
  "carrot": "🥕",
  "corn": "🌽",
  "broccoli": "🥦",
  "avocado": "🥑",
  "potato": "🥔",
  "onion": "🧅",
  "garlic": "🧄",
  "milk": "🥛",
  "juice": "🧃",
  "coffee": "☕",
  "tea": "🍵",
  "peanut": "🥜",
  "lollipop": "🍭",
  "sandwich": "🥪",
  "soup": "🍲",
  "noodle": "🍜",
  "pasta": "🍝",
  "rice": "🍚",
  "water": "💧",

  "heart": "❤️",
  "ball": "⚽",
  "balloon": "🎈",
  "gift": "🎁",
  "book": "📚",
  "pencil": "✏️",
  "crayon": "🖍️",
  "art": "🎨",
  "music": "🎵",
  "drum": "🥁",
  "guitar": "🎸",
  "piano": "🎹",
  "rocket": "🚀",
  "car": "🚗",
  "bus": "🚌",
  "train": "🚂",
  "airplane": "✈️",
  "boat": "⛵",
  "bike": "🚲",
  "house": "🏠",
  "castle": "🏰",
  "tent": "⛺",
  "school": "🏫",
  "headphones": "🎧",
  "phone": "📱",
  "camera": "📷",
  "computer": "💻",
  "clock": "🕐",
  "lamp": "💡",
  "key": "🔑",
  "umbrella": "☂️",
  "glasses": "👓",
  "hat": "🎩",
  "shoe": "👟",
  "shirt": "👕",
  "dress": "👗",
  "backpack": "🎒",
  "scissors": "✂️",
  "hammer": "🔨",
  "wrench": "🔧",
  "teddy": "🧸",
  "puzzle": "🧩",
  "dice": "🎲",
  "kite": "🪁",
  "slide": "🛝",
  "sled": "🛷",
  "skateboard": "🛹",
  "sword": "🗡️",
  "shield": "🛡️",
  "bell": "🔔",
  "door": "🚪",
  "bed": "🛏️",
  "bath": "🛁",
  "toilet": "🚽",
  "soap": "🧼",
  "candle": "🕯️",
  "map": "🗺️",

  "helicopter": "🚁",
  "tractor": "🚜",
  "ambulance": "🚑",
  "firetruck": "🚒",
  "police": "🚓",
  "taxi": "🚕",
  "truck": "🚚",
  "scooter": "🛴",
  "motorcycle": "🏍️",
  "ship": "🚢",
  "canoe": "🛶",

  "soccer": "⚽",
  "basketball": "🏀",
  "football": "🏈",
  "baseball": "⚾",
  "tennis": "🎾",
  "bowling": "🎳",
  "golf": "⛳",
  "skating": "⛸️",
  "skiing": "⛷️",
  "surfing": "🏄",
  "fishing": "🎣",

  "happy": "😊",
  "sad": "😢",
  "laugh": "😂",
  "love": "❤️",
  "cool": "😎",
  "silly": "🤪",
  "sleepy": "😴",
  "surprised": "😮",
  "think": "🤔",
  "wow": "🤩",
  "angry": "😠",
  "scared": "😨",
  "sick": "🤒",
  "dizzy": "😵",
  "nerd": "🤓",
  "party": "🥳",
  "wink": "😉",
  "shy": "🫣",
  "yuck": "🤢",

  "run": "🏃",
  "swim": "🏊",
  "dance": "💃",
  "sing": "🎤",
  "play": "🎸",
  "read": "📖",
  "write": "✍️",
  "paint": "🖌️",
  "explore": "🔍",
  "doodle": "🖌️",

  "yes": "✅",
  "no": "❌",
  "thumbsup": "👍",
  "clap": "👏",
  "wave": "👋",
  "hug": "🤗",
  "fire": "🔥",
  "sparkle": "✨",
  "magic": "🪄",
  "crown": "👑",
  "gem": "💎",
  "medal": "🏅",
  "trophy": "🏆",
  "flag": "🚩",
  "bomb": "💣",
  "lightning": "⚡",
  "poop": "💩",
  "skull": "💀",
  "eye": "👁️",
  "brain": "🧠",
  "tooth": "🦷",
  "bone": "🦴",
  "nose": "👃",
  "tongue": "👅",

  "circle": "🔴",
  "square": "🟦",
  "triangle": "🔺",
  "diamond": "🔷",

  "pumpkin": "🎃",
  "snowman": "☃️",
  "santa": "🎅",
  "present": "🎁",
  "firework": "🎆",

  ":)": "😊",
  ":-)": "😊",
  ":(": "😢",
  ":-(": "😢",
  ":D": "😂",
  ":-D": "😂",
  ";)": "😉",
  ";-)": "😉",
  ":P": "😛",
  ":-P": "😛",
  ":O": "😮",
  ":-O": "😮",
  ">:(": "😠",
  "<3": "💜"
}
